[
{
    "model": "services.masters",
    "pk": 1,
    "fields": {
        "name": "Елизавета",
        "level": "Топ-мастер",
        "photo": "masters/person_1.jpg",
        "description": "Какое то описание для мастера, заслуги, стаж и тд",
        "discount": "0.00"
    }
},
{
    "model": "services.masters",
    "pk": 2,
    "fields": {
        "name": "Екатерина",
        "level": "Топ-мастер",
        "photo": "masters/person_2.jpg",
        "description": "Какое то описание для мастера, заслуги, стаж и тд",
        "discount": "0.00"
    }
},
{
    "model": "services.masters",
    "pk": 3,
    "fields": {
        "name": "Иван",
        "level": "Мастер",
        "photo": "masters/person_3.jpg",
        "description": "Какое то описание для мастера, заслуги, стаж и тд",
        "discount": "20.00"
    }
},
{
    "model": "services.masters",
    "pk": 4,
    "fields": {
        "name": "Дарья",
        "level": "Топ-мастер",
        "photo": "masters/person_4.jpg",
        "description": "Какое то описание для мастера, заслуги, стаж и тд",
        "discount": "0.00"
    }
},
{
    "model": "services.masters",
    "pk": 5,
    "fields": {
        "name": "Руслана",
        "level": "Мастер",
        "photo": "masters/person_5.jpg",
        "description": "Какое то описание для мастера, заслуги, стаж и тд",
        "discount": "0.00"
    }
}
]
